octans/__init__.py
octans/catalgues.py
octans/errors.py
octans/kvw.py
octans/lc.py
octans/lc_model.py
octans/model_catalgues.py
octans/model_portal.py
octans/model_sky.py
octans/portal.py
octans/py.typed
octans/sky.py
octans/utils.py
octans-0.0.1b0.dist-info/LICENSE
octans-0.0.1b0.dist-info/METADATA
octans-0.0.1b0.dist-info/WHEEL
octans-0.0.1b0.dist-info/top_level.txt
octans-0.0.1b0.dist-info/RECORD
