Metadata-Version: 2.1
Name: octans
Version: 0.0.1b0
Summary: Observed CalculaTed diagrAm aNd lightcurveS
Home-page: https://github.com/mshemuni/octans/
Author: Mohammad S.Niaei
Author-email: m.shemuni@gmail.com
License: GNU/GPL V3
Keywords: Observed-Calculated,Lightcurve
Classifier: Programming Language :: Python :: 3
Classifier: Programming Language :: Python :: 3 :: Only
Classifier: Programming Language :: Python :: 3.10
Classifier: Programming Language :: Python :: 3.11
Classifier: Operating System :: MacOS
Classifier: Operating System :: Microsoft :: Windows
Classifier: Operating System :: POSIX :: Linux
Requires-Python: >=3.8
License-File: LICENSE
Requires-Dist: astropy
Requires-Dist: astroquery
Requires-Dist: beautifulsoup4
Requires-Dist: charset-normalizer
Requires-Dist: lightkurve
Requires-Dist: matplotlib
Requires-Dist: numpy
Requires-Dist: pandas
Requires-Dist: Requests
Requires-Dist: scipy
Requires-Dist: selenium
Requires-Dist: tqdm
Requires-Dist: trio
Requires-Dist: typing-extensions
Requires-Dist: webdriver-manager
Provides-Extra: testing
Requires-Dist: pytest; extra == "testing"
Requires-Dist: pytest-cov; extra == "testing"
Requires-Dist: mypy; extra == "testing"
Requires-Dist: flake8; extra == "testing"
Requires-Dist: tox; extra == "testing"
